coinmarketcap_scrapi/__init__.py
coinmarketcap_scrapi/cmc_uteis.py
coinmarketcap_scrapi/coinmarketcap_scrapi.py
coinmarketcap_scrapi/excepcions.py
coinmarketcap_scrapi-1.0.dist-info/LICENSE
coinmarketcap_scrapi-1.0.dist-info/METADATA
coinmarketcap_scrapi-1.0.dist-info/WHEEL
coinmarketcap_scrapi-1.0.dist-info/top_level.txt
coinmarketcap_scrapi-1.0.dist-info/RECORD
